Workbook

Sheet Presupuesto
A1: Nombre del Proyecto: | B1: HOPARK
A2: Fecha de iniciación: | B2: 44200 | E2: Fecha de finalización: | G2: 43845
B5: Enero | C5: Febrero | D5: Marzo | E5: Abril | F5: Mayo | G5: Junio | H5: Julio | I5: Agosto | J5: Septiembre | K5: Octubre | L5: Noviembre | M5: Diciembre
A6: Ingresos
A7: Ingresos por avances | B7: =$M$20*0.15 -> 7500 | C7: =$M$20*0.15 -> 7500 | E7: =$M$20*0.15 -> 7500 | G7: =$M$20*0.15 -> 7500 | I7: =$M$20*0.15 -> 7500 | K7: =$M$20*0.15 -> 7500 | M7: =$M$20*0.1 -> 5000
A8: Total ingresos
A10: Egresos
A11: Gastos mensuales | B11: ='Gastos mensuales'!B21 -> 2440 | C11: ='Gastos mensuales'!C21 -> 165 | D11: ='Gastos mensuales'!D21 -> 165 | E11: ='Gastos mensuales'!E21 -> 240 | F11: ='Gastos mensuales'!F21 -> 2065 | G11: ='Gastos mensuales'!G21 -> 165 | H11: ='Gastos mensuales'!H21 -> 240 | I11: ='Gastos mensuales'!I21 -> 165 | ... M11: ='Gastos mensuales'!M21 -> 165
A12: Gastos personales | B12: =$M$21*'Gastos personales'!B10 -> 405 | C12: =$M$21*'Gastos personales'!C10 -> 405 | D12: =$M$21*'Gastos personales'!D10 -> 405 | E12: =$M$21*'Gastos personales'!E10 -> 405 | F12: =$M$21*'Gastos personales'!F10 -> 405 | G12: =$M$21*'Gastos personales'!G10 -> 405 | H12: =$M$21*'Gastos personales'!H10 -> 405 | I12: =$M$21*'Gastos personales'!I10 -> 405 | ... M12: =$M$21*'Gastos personales'!M10 -> 405
A13: Gastos por sueldos | B13: =$M$22*$M$21 -> 2277 | C13: =$M$22*$M$21 -> 2277 | D13: =$M$22*$M$21 -> 2277 | E13: =$M$22*$M$21 -> 2277 | F13: =$M$22*$M$21 -> 2277 | G13: =$M$22*$M$21 -> 2277 | H13: =$M$22*$M$21 -> 2277 | I13: =$M$22*$M$21 -> 2277 | ... M13: =$M$22*$M$21 -> 2277
A14: Total egresos | B14: =SUM(B11:B13) -> 5122 | C14: =SUM(C11:C13) -> 2847 | D14: =SUM(D11:D13) -> 2847 | E14: =SUM(E11:E13) -> 2922 | F14: =SUM(F11:F13) -> 4747 | G14: =SUM(G11:G13) -> 2847 | H14: =SUM(H11:H13) -> 2922 | I14: =SUM(I11:I13) -> 2847 | ... M14: =SUM(M11:M13) -> 2847
A16: Saldo Final en Caja | B16: =B7-B14 -> 2378 | C16: =C7-C14 -> 4653 | D16: =D7-D14 -> -2847 | E16: =E7-E14 -> 4578 | F16: =F7-F14 -> -4747 | G16: =G7-G14 -> 4653 | H16: =H7-H14 -> -2922 | I16: =I7-I14 -> 4653 | ... M16: =M7-M14 -> 2153
A17: Flujo acumulado | B17: =B16 -> 2378 | C17: =C16+B17 -> 7031 | D17: =D16+C17 -> 4184 | E17: =E16+D17 -> 8762 | F17: =F16+E17 -> 4015 | G17: =G16+F17 -> 8668 | H17: =H16+G17 -> 5746 | I17: =I16+H17 -> 10399 | J17: =J16+I17 -> 5652 | ... L17: =L16+K17 -> 7383 | M17: =M16+I17 -> 12552
K20: Valor del Proyecto: | M20: 50000
K21: No. de personas: | M21: 3
K22: Sueldo: | M22: 759

Sheet Gastos mensuales
B1: Enero | C1: Febrero | D1: Marzo | E1: Abril | F1: Mayo | G1: Junio | H1: Julio | I1: Agosto | J1: Septiembre | K1: Octubre | L1: Noviembre | M1: Diciembre
A2: Suministros de oficinas
A3: CDs | B3: 10 | E3: 10 | H3: 10 | K3: 10
A4: Hojas | B4: 25 | C4: 25 | D4: 25 | E4: 25 | F4: 25 | G4: 25 | H4: 25 | I4: 25 | J4: 25 | K4: 25 | L4: 25 | M4: 25
A5: Tinta | B5: 35 | C5: 35 | D5: 35 | E5: 35 | F5: 35 | G5: 35 | H5: 35 | I5: 35 | J5: 35 | K5: 35 | L5: 35 | M5: 35
A6: Carpetas | B6: 20 | E6: 20 | H6: 20 | K6: 20
A7: Bolígrafos | B7: 15 | E7: 15 | H7: 15 | K7: 15
A8: Lapicero | B8: 10 | E8: 10 | H8: 10 | K8: 10
A9: Minas | B9: 10 | E9: 10 | H9: 10 | K9: 10
A10: Borrador | B10: 10 | E10: 10 | H10: 10 | K10: 10
A11: Hardware
A12: Memoria | B12: 300
A13: Laptop | B13: 700 | F13: 700 | J13: 700
A14: Celular | B14: 200 | F14: 200 | J14: 200
A15: Servidor | B15: 1000 | F15: 1000 | J15: 1000
A16: Servicios Básicos
A17: Agua | B17: 30 | C17: 30 | D17: 30 | E17: 30 | F17: 30 | G17: 30 | H17: 30 | I17: 30 | J17: 30 | K17: 30 | L17: 30 | M17: 30
A18: Teléfono | B18: 30 | C18: 30 | D18: 30 | E18: 30 | F18: 30 | G18: 30 | H18: 30 | I18: 30 | J18: 30 | K18: 30 | L18: 30 | M18: 30
A19: Energía Eléctrica | B19: 45 | C19: 45 | D19: 45 | E19: 45 | F19: 45 | G19: 45 | H19: 45 | I19: 45 | J19: 45 | K19: 45 | L19: 45 | M19: 45
A21: Total | B21: =SUM(B3:B19) -> 2440 | C21: =SUM(C3:C19) -> 165 | D21: =SUM(D3:D19) -> 165 | E21: =SUM(E3:E19) -> 240 | F21: =SUM(F3:F19) -> 2065 | G21: =SUM(G3:G19) -> 165 | H21: =SUM(H3:H19) -> 240 | I21: =SUM(I3:I19) -> 165 | ... M21: =SUM(M3:M19) -> 165

Sheet Gastos personales
B1: Enero | C1: Febrero | D1: Marzo | E1: Abril | F1: Mayo | G1: Junio | H1: Julio | I1: Agosto | J1: Septiembre | K1: Octubre | L1: Noviembre | M1: Diciembre
A2: Transporte
A3: Taxi | B3: 30 | C3: 30 | D3: 30 | E3: 30 | F3: 30 | G3: 30 | H3: 30 | I3: 30 | J3: 30 | K3: 30 | L3: 30 | M3: 30
A4: Alimentación
A5: Almuerzo | B5: 30 | C5: 30 | D5: 30 | E5: 30 | F5: 30 | G5: 30 | H5: 30 | I5: 30 | J5: 30 | K5: 30 | L5: 30 | M5: 30
A6: Merienda | B6: 30 | C6: 30 | D6: 30 | E6: 30 | F6: 30 | G6: 30 | H6: 30 | I6: 30 | J6: 30 | K6: 30 | L6: 30 | M6: 30
A7: Otros | B7: 20 | C7: 20 | D7: 20 | E7: 20 | F7: 20 | G7: 20 | H7: 20 | I7: 20 | J7: 20 | K7: 20 | L7: 20 | M7: 20
A8: Comunicación
A9: Internet | B9: 25 | C9: 25 | D9: 25 | E9: 25 | F9: 25 | G9: 25 | H9: 25 | I9: 25 | J9: 25 | K9: 25 | L9: 25 | M9: 25
A10: Total | B10: =SUM(B3:B9) -> 135 | C10: =SUM(C3:C9) -> 135 | D10: =SUM(D3:D9) -> 135 | E10: =SUM(E3:E9) -> 135 | F10: =SUM(F3:F9) -> 135 | G10: =SUM(G3:G9) -> 135 | H10: =SUM(H3:H9) -> 135 | I10: =SUM(I3:I9) -> 135 | ... M10: =SUM(M3:M9) -> 135

Sheet Sheet4
D2: FACTURACION
A5: Valor que quiero recibir | B5: 1000
I6: UD VA A RECIBIR ESTO
F7: Valor Base: | G7: 55555.55 | I7: =G7-G8 -> 49999.995
F8: Impuesto a la Renta | G8: =G7*0.1 -> 5555.555 | H8: Retener
A9: Impuesto a la Renta | B9: 0.1 | D9: Valor Base | F9: IVA: | G9: =G7*0.12 -> 6666.666 | H9: Retener
A10: Impuesto al IVA | B10: 0.12 | D10: Subtotal | F10: Valor Final: | G10: =G9+G7 -> 62222.216
